MANIFEST.in
README.rst
setup.py
tw2/__init__.py
tw2.rrd.egg-info/PKG-INFO
tw2.rrd.egg-info/SOURCES.txt
tw2.rrd.egg-info/dependency_links.txt
tw2.rrd.egg-info/entry_points.txt
tw2.rrd.egg-info/namespace_packages.txt
tw2.rrd.egg-info/not-zip-safe
tw2.rrd.egg-info/requires.txt
tw2.rrd.egg-info/top_level.txt
tw2/rrd/__init__.py
tw2/rrd/samples.py
tw2/rrd/data/make-rrds-from-sources.sh
tw2/rrd/data/32/flat/cpu_aidle.rrd
tw2/rrd/data/32/flat/cpu_idle.rrd
tw2/rrd/data/32/flat/cpu_nice.rrd
tw2/rrd/data/32/flat/cpu_num.rrd
tw2/rrd/data/32/flat/cpu_speed.rrd
tw2/rrd/data/32/flat/cpu_system.rrd
tw2/rrd/data/32/flat/cpu_user.rrd
tw2/rrd/data/32/flat/cpu_wio.rrd
tw2/rrd/data/32/nested/filename/Brazil/backtrack.rrd
tw2/rrd/data/32/nested/filename/Brazil/centos.rrd
tw2/rrd/data/32/nested/filename/Brazil/epel.rrd
tw2/rrd/data/32/nested/filename/Brazil/fedora.rrd
tw2/rrd/data/32/nested/filename/Brazil/opensuse.rrd
tw2/rrd/data/32/nested/filename/Canada/CPAN.rrd
tw2/rrd/data/32/nested/filename/Canada/archlinux.rrd
tw2/rrd/data/32/nested/filename/Canada/backtrack.rrd
tw2/rrd/data/32/nested/filename/Canada/centos.rrd
tw2/rrd/data/32/nested/filename/Canada/epel.rrd
tw2/rrd/data/32/nested/filename/Canada/fedora.rrd
tw2/rrd/data/32/nested/filename/Canada/opensuse.rrd
tw2/rrd/data/32/nested/filename/Canada/ubuntu.rrd
tw2/rrd/data/32/nested/filename/China/archlinux.rrd
tw2/rrd/data/32/nested/filename/China/backtrack.rrd
tw2/rrd/data/32/nested/filename/China/centos.rrd
tw2/rrd/data/32/nested/filename/China/fedora.rrd
tw2/rrd/data/32/nested/filename/China/ubuntu-releases.rrd
tw2/rrd/data/32/nested/filename/France/archlinux.rrd
tw2/rrd/data/32/nested/filename/Germany/centos.rrd
tw2/rrd/data/32/nested/filename/Germany/opensuse.rrd
tw2/rrd/data/32/nested/filename/Greece/kdemod.rrd
tw2/rrd/data/32/nested/filename/India/opensuse.rrd
tw2/rrd/data/32/nested/filename/Italy/opensuse.rrd
tw2/rrd/data/32/nested/filename/Malaysia/backtrack.rrd
tw2/rrd/data/32/nested/filename/Mexico/archlinux.rrd
tw2/rrd/data/32/nested/filename/Mexico/centos.rrd
tw2/rrd/data/32/nested/filename/Mexico/epel.rrd
tw2/rrd/data/32/nested/filename/Mexico/fedora.rrd
tw2/rrd/data/32/nested/filename/Peru/centos.rrd
tw2/rrd/data/32/nested/filename/Peru/epel.rrd
